{"nodes": [{"id": "c_users_ebby_trae_projects_myfrigo_context_diagnosticcontext_tsx", "label": "DiagnosticContext.tsx", "file_type": "code", "source_file": "C:\\Users\\Ebby\\Trae Projects\\myfrigo\\context\\DiagnosticContext.tsx", "source_location": "L1"}, {"id": "context_diagnosticcontext_diagnosticstate", "label": "DiagnosticState", "file_type": "code", "source_file": "C:\\Users\\Ebby\\Trae Projects\\myfrigo\\context\\DiagnosticContext.tsx", "source_location": "L14"}, {"id": "context_diagnosticcontext_diagnosticaction", "label": "DiagnosticAction", "file_type": "code", "source_file": "C:\\Users\\Ebby\\Trae Projects\\myfrigo\\context\\DiagnosticContext.tsx", "source_location": "L22"}, {"id": "context_diagnosticcontext_initialstate", "label": "initialState", "file_type": "code", "source_file": "C:\\Users\\Ebby\\Trae Projects\\myfrigo\\context\\DiagnosticContext.tsx", "source_location": "L30"}, {"id": "context_diagnosticcontext_diagnosticreducer", "label": "diagnosticReducer()", "file_type": "code", "source_file": "C:\\Users\\Ebby\\Trae Projects\\myfrigo\\context\\DiagnosticContext.tsx", "source_location": "L38"}, {"id": "context_diagnosticcontext_diagnosticcontexttype", "label": "DiagnosticContextType", "file_type": "code", "source_file": "C:\\Users\\Ebby\\Trae Projects\\myfrigo\\context\\DiagnosticContext.tsx", "source_location": "L80"}, {"id": "context_diagnosticcontext_diagnosticcontext", "label": "DiagnosticContext", "file_type": "code", "source_file": "C:\\Users\\Ebby\\Trae Projects\\myfrigo\\context\\DiagnosticContext.tsx", "source_location": "L92"}, {"id": "context_diagnosticcontext_diagnosticproviderprops", "label": "DiagnosticProviderProps", "file_type": "code", "source_file": "C:\\Users\\Ebby\\Trae Projects\\myfrigo\\context\\DiagnosticContext.tsx", "source_location": "L94"}, {"id": "context_diagnosticcontext_diagnosticprovider", "label": "DiagnosticProvider()", "file_type": "code", "source_file": "C:\\Users\\Ebby\\Trae Projects\\myfrigo\\context\\DiagnosticContext.tsx", "source_location": "L100"}, {"id": "context_diagnosticcontext_usediagnosticcontext", "label": "useDiagnosticContext()", "file_type": "code", "source_file": "C:\\Users\\Ebby\\Trae Projects\\myfrigo\\context\\DiagnosticContext.tsx", "source_location": "L162"}], "edges": [{"source": "c_users_ebby_trae_projects_myfrigo_context_diagnosticcontext_tsx", "target": "react", "relation": "imports_from", "context": "import", "confidence": "EXTRACTED", "source_file": "C:\\Users\\Ebby\\Trae Projects\\myfrigo\\context\\DiagnosticContext.tsx", "source_location": "L11", "weight": 1.0}, {"source": "c_users_ebby_trae_projects_myfrigo_context_diagnosticcontext_tsx", "target": "c_users_ebby_trae_projects_myfrigo_hooks_usediagnostictests_ts", "relation": "imports_from", "context": "import", "confidence": "EXTRACTED", "source_file": "C:\\Users\\Ebby\\Trae Projects\\myfrigo\\context\\DiagnosticContext.tsx", "source_location": "L12", "weight": 1.0}, {"source": "c_users_ebby_trae_projects_myfrigo_context_diagnosticcontext_tsx", "target": "hooks_usediagnostictests_testresult", "relation": "imports", "context": "import", "confidence": "EXTRACTED", "source_file": "C:\\Users\\Ebby\\Trae Projects\\myfrigo\\context\\DiagnosticContext.tsx", "source_location": "L12", "weight": 1.0}, {"source": "c_users_ebby_trae_projects_myfrigo_context_diagnosticcontext_tsx", "target": "hooks_usediagnostictests_diagnostictest", "relation": "imports", "context": "import", "confidence": "EXTRACTED", "source_file": "C:\\Users\\Ebby\\Trae Projects\\myfrigo\\context\\DiagnosticContext.tsx", "source_location": "L12", "weight": 1.0}, {"source": "c_users_ebby_trae_projects_myfrigo_context_diagnosticcontext_tsx", "target": "context_diagnosticcontext_diagnosticstate", "relation": "contains", "confidence": "EXTRACTED", "source_file": "C:\\Users\\Ebby\\Trae Projects\\myfrigo\\context\\DiagnosticContext.tsx", "source_location": "L14", "weight": 1.0}, {"source": "c_users_ebby_trae_projects_myfrigo_context_diagnosticcontext_tsx", "target": "context_diagnosticcontext_diagnosticaction", "relation": "contains", "confidence": "EXTRACTED", "source_file": "C:\\Users\\Ebby\\Trae Projects\\myfrigo\\context\\DiagnosticContext.tsx", "source_location": "L22", "weight": 1.0}, {"source": "c_users_ebby_trae_projects_myfrigo_context_diagnosticcontext_tsx", "target": "context_diagnosticcontext_initialstate", "relation": "contains", "confidence": "EXTRACTED", "source_file": "C:\\Users\\Ebby\\Trae Projects\\myfrigo\\context\\DiagnosticContext.tsx", "source_location": "L30", "weight": 1.0}, {"source": "c_users_ebby_trae_projects_myfrigo_context_diagnosticcontext_tsx", "target": "context_diagnosticcontext_diagnosticreducer", "relation": "contains", "confidence": "EXTRACTED", "source_file": "C:\\Users\\Ebby\\Trae Projects\\myfrigo\\context\\DiagnosticContext.tsx", "source_location": "L38", "weight": 1.0}, {"source": "c_users_ebby_trae_projects_myfrigo_context_diagnosticcontext_tsx", "target": "context_diagnosticcontext_diagnosticcontexttype", "relation": "contains", "confidence": "EXTRACTED", "source_file": "C:\\Users\\Ebby\\Trae Projects\\myfrigo\\context\\DiagnosticContext.tsx", "source_location": "L80", "weight": 1.0}, {"source": "c_users_ebby_trae_projects_myfrigo_context_diagnosticcontext_tsx", "target": "context_diagnosticcontext_diagnosticcontext", "relation": "contains", "confidence": "EXTRACTED", "source_file": "C:\\Users\\Ebby\\Trae Projects\\myfrigo\\context\\DiagnosticContext.tsx", "source_location": "L92", "weight": 1.0}, {"source": "c_users_ebby_trae_projects_myfrigo_context_diagnosticcontext_tsx", "target": "context_diagnosticcontext_diagnosticproviderprops", "relation": "contains", "confidence": "EXTRACTED", "source_file": "C:\\Users\\Ebby\\Trae Projects\\myfrigo\\context\\DiagnosticContext.tsx", "source_location": "L94", "weight": 1.0}, {"source": "c_users_ebby_trae_projects_myfrigo_context_diagnosticcontext_tsx", "target": "context_diagnosticcontext_diagnosticprovider", "relation": "contains", "confidence": "EXTRACTED", "source_file": "C:\\Users\\Ebby\\Trae Projects\\myfrigo\\context\\DiagnosticContext.tsx", "source_location": "L100", "weight": 1.0}, {"source": "c_users_ebby_trae_projects_myfrigo_context_diagnosticcontext_tsx", "target": "context_diagnosticcontext_usediagnosticcontext", "relation": "contains", "confidence": "EXTRACTED", "source_file": "C:\\Users\\Ebby\\Trae Projects\\myfrigo\\context\\DiagnosticContext.tsx", "source_location": "L162", "weight": 1.0}], "raw_calls": [{"caller_nid": "context_diagnosticcontext_diagnosticprovider", "callee": "useReducer", "is_member_call": false, "source_file": "C:\\Users\\Ebby\\Trae Projects\\myfrigo\\context\\DiagnosticContext.tsx", "source_location": "L105"}, {"caller_nid": "context_diagnosticcontext_usediagnosticcontext", "callee": "useContext", "is_member_call": false, "source_file": "C:\\Users\\Ebby\\Trae Projects\\myfrigo\\context\\DiagnosticContext.tsx", "source_location": "L163"}]}