{"nodes": [{"id": "c_users_ebby_trae_projects_myfrigo_hooks_usequantitycalculation_ts", "label": "useQuantityCalculation.ts", "file_type": "code", "source_file": "C:\\Users\\Ebby\\Trae Projects\\myfrigo\\hooks\\useQuantityCalculation.ts", "source_location": "L1"}, {"id": "hooks_usequantitycalculation_quantitycalculationresult", "label": "QuantityCalculationResult", "file_type": "code", "source_file": "C:\\Users\\Ebby\\Trae Projects\\myfrigo\\hooks\\useQuantityCalculation.ts", "source_location": "L14"}, {"id": "hooks_usequantitycalculation_validationresult", "label": "ValidationResult", "file_type": "code", "source_file": "C:\\Users\\Ebby\\Trae Projects\\myfrigo\\hooks\\useQuantityCalculation.ts", "source_location": "L22"}, {"id": "hooks_usequantitycalculation_usequantitycalculation", "label": "useQuantityCalculation()", "file_type": "code", "source_file": "C:\\Users\\Ebby\\Trae Projects\\myfrigo\\hooks\\useQuantityCalculation.ts", "source_location": "L27"}], "edges": [{"source": "c_users_ebby_trae_projects_myfrigo_hooks_usequantitycalculation_ts", "target": "react", "relation": "imports_from", "context": "import", "confidence": "EXTRACTED", "source_file": "C:\\Users\\Ebby\\Trae Projects\\myfrigo\\hooks\\useQuantityCalculation.ts", "source_location": "L11", "weight": 1.0}, {"source": "c_users_ebby_trae_projects_myfrigo_hooks_usequantitycalculation_ts", "target": "c_users_ebby_trae_projects_myfrigo_types_product_ts", "relation": "imports_from", "context": "import", "confidence": "EXTRACTED", "source_file": "C:\\Users\\Ebby\\Trae Projects\\myfrigo\\hooks\\useQuantityCalculation.ts", "source_location": "L12", "weight": 1.0}, {"source": "c_users_ebby_trae_projects_myfrigo_hooks_usequantitycalculation_ts", "target": "types_product_quantity", "relation": "imports", "context": "import", "confidence": "EXTRACTED", "source_file": "C:\\Users\\Ebby\\Trae Projects\\myfrigo\\hooks\\useQuantityCalculation.ts", "source_location": "L12", "weight": 1.0}, {"source": "c_users_ebby_trae_projects_myfrigo_hooks_usequantitycalculation_ts", "target": "hooks_usequantitycalculation_quantitycalculationresult", "relation": "contains", "confidence": "EXTRACTED", "source_file": "C:\\Users\\Ebby\\Trae Projects\\myfrigo\\hooks\\useQuantityCalculation.ts", "source_location": "L14", "weight": 1.0}, {"source": "c_users_ebby_trae_projects_myfrigo_hooks_usequantitycalculation_ts", "target": "hooks_usequantitycalculation_validationresult", "relation": "contains", "confidence": "EXTRACTED", "source_file": "C:\\Users\\Ebby\\Trae Projects\\myfrigo\\hooks\\useQuantityCalculation.ts", "source_location": "L22", "weight": 1.0}, {"source": "c_users_ebby_trae_projects_myfrigo_hooks_usequantitycalculation_ts", "target": "hooks_usequantitycalculation_usequantitycalculation", "relation": "contains", "confidence": "EXTRACTED", "source_file": "C:\\Users\\Ebby\\Trae Projects\\myfrigo\\hooks\\useQuantityCalculation.ts", "source_location": "L27", "weight": 1.0}], "raw_calls": [{"caller_nid": "hooks_usequantitycalculation_usequantitycalculation", "callee": "useMemo", "is_member_call": false, "source_file": "C:\\Users\\Ebby\\Trae Projects\\myfrigo\\hooks\\useQuantityCalculation.ts", "source_location": "L30"}, {"caller_nid": "hooks_usequantitycalculation_usequantitycalculation", "callee": "useMemo", "is_member_call": false, "source_file": "C:\\Users\\Ebby\\Trae Projects\\myfrigo\\hooks\\useQuantityCalculation.ts", "source_location": "L31"}, {"caller_nid": "hooks_usequantitycalculation_usequantitycalculation", "callee": "useMemo", "is_member_call": false, "source_file": "C:\\Users\\Ebby\\Trae Projects\\myfrigo\\hooks\\useQuantityCalculation.ts", "source_location": "L32"}, {"caller_nid": "hooks_usequantitycalculation_usequantitycalculation", "callee": "useMemo", "is_member_call": false, "source_file": "C:\\Users\\Ebby\\Trae Projects\\myfrigo\\hooks\\useQuantityCalculation.ts", "source_location": "L34"}, {"caller_nid": "hooks_usequantitycalculation_usequantitycalculation", "callee": "useCallback", "is_member_call": false, "source_file": "C:\\Users\\Ebby\\Trae Projects\\myfrigo\\hooks\\useQuantityCalculation.ts", "source_location": "L43"}]}